{
  "SPACING-M": "1.25rem",
  "SPACING-XS": "0.5rem",
  "SPACING-LG": "2rem",
  "COLOR-BRAND-LIGHT-GREY": "#E3DFD7",
  "COLOR-BRAND-DARK-GREY": "#141413",
  "COLOR-BACKGROUND-RADIO": "#FFFFFF",
  "BORDER-RADIUS-BUTTONS": "100px",
  "COLOR-BORDER-BASE": "#44433F",
  "COLOR-BACKGROUND-FORM-ELEMENT": "#353432",
  "COLOR-TAB-ACTIVE": "#FFFFFF",
  "SPACING-XXS": "0.25rem",
  "COLOR-BACKGROUND-TOGGLE": "#353432",
  "SPACING-S": "0.75rem",
  "COLOR-TEXT-FORM-ELEMENT": "#FFFFFF",
  "DURATION-BASE": "500ms",
  "COLOR-BACKGROUND-APP": "#353432",
  "BORDER-RADIUS-FORM-ELEMENT": "100px",
  "COLOR-BACKGROUND-PAGE-TITLE": "#222222",
  "COLOR-BORDER-BRAND": "#FF671B",
  "COLOR-BACKGROUND-SIDE_NAV": "#222222",
  "COLOR-BACKGROUND-DISABLED": "#D3D3D3",
  "COLOR-TEXT-BRAND": "#FF671B",
  "COLOR-BACKGROUND-MESSAGE": "#222222",
  "COLOR-BACKGROUND-BRAND": "#FF671B",
  "COLOR-BACKGROUND-MESSAGE-ICON": "#141414",
  "COLOR-TEXT-01": "#FFFFFF",
  "COLOR-TEXT-INVERSE": "#353432",
  "SPACING-BASE": "1rem",
  "FONT-FAMILY-BASE": "Arial, Helvetica, sans-serif",
  "COLOR-BACKGROUND-MESSAGE-ICON-LIGHT": "#222222",
  "COLOR-BACKGROUND-SEARCH": "#353432",
  "SPACING-XL": "2.5rem",
  "COLOR-WHITE": "#FFFFFF",
  "FONT-SIZE-BASE": "1rem",
  "COLOR-BACKGROUND-ACCENT": "#44433F"
}